gaiaoffline/__init__.py
gaiaoffline/gaiaoffline.py
gaiaoffline/utils.py
gaiaoffline-1.0.3.dist-info/LICENSE
gaiaoffline-1.0.3.dist-info/METADATA
gaiaoffline-1.0.3.dist-info/WHEEL
gaiaoffline-1.0.3.dist-info/RECORD
